fleetpings/__init__.py
fleetpings/admin.py
fleetpings/app_settings.py
fleetpings/apps.py
fleetpings/auth_hooks.py
fleetpings/constants.py
fleetpings/form.py
fleetpings/managers.py
fleetpings/models.py
fleetpings/providers.py
fleetpings/urls.py
fleetpings/views.py
fleetpings/helper/__init__.py
fleetpings/helper/discord_webhook.py
fleetpings/helper/eve_images.py
fleetpings/helper/ping_context.py
fleetpings/helper/urls.py
fleetpings/locale/django.pot
fleetpings/locale/cs_CZ/LC_MESSAGES/django.mo
fleetpings/locale/cs_CZ/LC_MESSAGES/django.po
fleetpings/locale/de/LC_MESSAGES/django.mo
fleetpings/locale/de/LC_MESSAGES/django.po
fleetpings/locale/es/LC_MESSAGES/django.mo
fleetpings/locale/es/LC_MESSAGES/django.po
fleetpings/locale/fr_FR/LC_MESSAGES/django.mo
fleetpings/locale/fr_FR/LC_MESSAGES/django.po
fleetpings/locale/it_IT/LC_MESSAGES/django.mo
fleetpings/locale/it_IT/LC_MESSAGES/django.po
fleetpings/locale/ja/LC_MESSAGES/django.mo
fleetpings/locale/ja/LC_MESSAGES/django.po
fleetpings/locale/ko_KR/LC_MESSAGES/django.mo
fleetpings/locale/ko_KR/LC_MESSAGES/django.po
fleetpings/locale/nl_NL/LC_MESSAGES/django.mo
fleetpings/locale/nl_NL/LC_MESSAGES/django.po
fleetpings/locale/pl_PL/LC_MESSAGES/django.mo
fleetpings/locale/pl_PL/LC_MESSAGES/django.po
fleetpings/locale/ru/LC_MESSAGES/django.mo
fleetpings/locale/ru/LC_MESSAGES/django.po
fleetpings/locale/sk/LC_MESSAGES/django.mo
fleetpings/locale/sk/LC_MESSAGES/django.po
fleetpings/locale/uk/LC_MESSAGES/django.mo
fleetpings/locale/uk/LC_MESSAGES/django.po
fleetpings/locale/zh_Hans/LC_MESSAGES/django.mo
fleetpings/locale/zh_Hans/LC_MESSAGES/django.po
fleetpings/migrations/0001_initial.py
fleetpings/migrations/0002_webhook_is_embed_description_change.py
fleetpings/migrations/0003_fleetdoctrine_link.py
fleetpings/migrations/0004_auto_20200915_1617.py
fleetpings/migrations/0005_fleettype_restricted_to_group.py
fleetpings/migrations/0006_fleetdoctrine_restricted_to_group.py
aa_fleetpings-3.9.1.dist-info/METADATA
aa_fleetpings-3.9.1.dist-info/WHEEL
aa_fleetpings-3.9.1.dist-info/licenses/LICENSE
aa_fleetpings-3.9.1.dist-info/RECORD
